fluence/__init__.py
fluence/adaptive/__init__.py
fluence/adaptive/entmax.py
fluence/adaptive/layerdrop.py
fluence/adaptive/span.py
fluence/datasets/__init__.py
fluence/datasets/siamese_dataset.py
fluence/meta/__init__.py
fluence/meta/meta_args.py
fluence/meta/meta_dataset.py
fluence/meta/meta_trainer.py
fluence/models/__init__.py
fluence/models/orthogonal.py
fluence/models/siamese_model.py
fluence/optim/__init__.py
fluence/optim/lamb.py
fluence/optim/lookahead.py
fluence/sampling/__init__.py
fluence/sampling/clustering.py
fluence/utils/__init__.py
fluence/utils/siamese_utils.py
Fluence-0.1.7.dist-info/LICENSE
Fluence-0.1.7.dist-info/METADATA
Fluence-0.1.7.dist-info/WHEEL
Fluence-0.1.7.dist-info/top_level.txt
Fluence-0.1.7.dist-info/RECORD
