Metadata-Version: 2.1
Name: Fluence
Version: 0.1.7
Summary: Pytorch based deep learning library focussed on providing computationally efficient low resource methods and algorithms for NLP
Home-page: https://github.com/prajjwal1/fluence
Author: Prajjwal Bhargava
Author-email: prajjwalin@pm.me
License: Apache
Keywords: attention pytorch transformers
Platform: UNKNOWN
Classifier: Development Status :: 2 - Pre-Alpha
Classifier: Intended Audience :: Developers
Classifier: Intended Audience :: Education
Classifier: Intended Audience :: Science/Research
Classifier: License :: OSI Approved :: Apache Software License
Classifier: Operating System :: OS Independent
Classifier: Programming Language :: Python :: 3
Classifier: Programming Language :: Python :: 3.6
Classifier: Programming Language :: Python :: 3.7
Classifier: Topic :: Scientific/Engineering :: Artificial Intelligence
Requires-Python: >=3.6
Requires-Dist: numpy
Requires-Dist: tqdm (>=4.27)
Requires-Dist: transformers
Requires-Dist: higher
Requires-Dist: pandas
Requires-Dist: dataclasses ; python_version < "3.7"
